<?xml version="1.0" encoding="UTF-8"?>
<mdRecord xmlns="http://dplava.lib.virginia.edu"
          xmlns:dc="http://purl.org/dc/elements/1.1/"
          xmlns:dcterms="http://purl.org/dc/terms/"
          xmlns:edm="http://www.europeana.eu/schemas/edm/"
          xmlns:rdf="http://www.w3.org/1999/02/22-rdf-syntax-ns#"
          xmlns:xsi="http://www.w3.org/2001/XMLSchema-instance"
          xsi:schemaLocation="http://dplava.lib.virginia.edu/dplava.xsd">
   <dcterms:title>Letter, Susan Wheeler Decatur to George Hay, circa 1807  </dcterms:title>
   <dcterms:creator>Decatur, Susan Wheeler</dcterms:creator>
   <dcterms:contributor>Hay, George, 1765-1830</dcterms:contributor>
   <dcterms:created>c. 1807</dcterms:created>
   <dcterms:description>Letter discussing the court martial of Commodore James Barron, who would later kill Commodore Stephen Decatur in duel in 1820. Autograph letter signed, 1 page, with integral address panel. </dcterms:description>
   <dcterms:medium>Manuscript</dcterms:medium>
   <dcterms:medium>Correspondence</dcterms:medium>
   <dcterms:type>Text</dcterms:type>
   <dcterms:identifier>DA_003522</dcterms:identifier>
   <dcterms:rights>http://rightsstatements.org/vocab/NKC/1.0/</dcterms:rights>
   <dcterms:isPartOf>Peter Family Papers</dcterms:isPartOf>
   <dcterms:language>English</dcterms:language>
   <edm:isShownAt>http://cdm16829.contentdm.oclc.org/cdm/ref/collection/p16829coll39/id/66</edm:isShownAt>
   <edm:preview>http://server16829.contentdm.oclc.org/cgi-bin/thumbnail.exe?CISOROOT=/p16829coll39&amp;CISOPTR=66</edm:preview>
   <dcterms:provenance>George Washington's Mount Vernon</dcterms:provenance>
</mdRecord>
