<?xml version="1.0" encoding="UTF-8"?>
<mdRecord xmlns="http://dplava.lib.virginia.edu"
          xmlns:dc="http://purl.org/dc/elements/1.1/"
          xmlns:dcterms="http://purl.org/dc/terms/"
          xmlns:edm="http://www.europeana.eu/schemas/edm/"
          xmlns:rdf="http://www.w3.org/1999/02/22-rdf-syntax-ns#"
          xmlns:xsi="http://www.w3.org/2001/XMLSchema-instance"
          xsi:schemaLocation="http://dplava.lib.virginia.edu/dplava.xsd">
   <dcterms:title>Laurance H. Hart (as George Washington) at Mount Vernon, 1932 </dcterms:title>
   <dcterms:contributor>Hart, Laurance H.</dcterms:contributor>
   <dcterms:created>1932</dcterms:created>
   <dcterms:description>Black and white photograph of Laurance H. Hart, George Washington impersonator standing on the east lawn at Mount Vernon. According to the 1932 Bicentennial Commission report on events, Mr. Hart, dressed in colonial attire, conducted an "interview with George Washington" with his wife acting as a modern reporter. The interview did not take place at Mount Vernon.  </dcterms:description>
   <dcterms:subject>Mount Vernon (Va. : Estate)</dcterms:subject>
   <dcterms:medium>Photographic prints</dcterms:medium>
   <dcterms:type>Still image</dcterms:type>
   <dcterms:identifier>DA_002627</dcterms:identifier>
   <dcterms:rights>http://rightsstatements.org/vocab/NoC-US/1.0/</dcterms:rights>
   <dcterms:isPartOf>Historical Photograph Collection </dcterms:isPartOf>
   <dcterms:language>English</dcterms:language>
   <edm:isShownAt>http://cdm16829.contentdm.oclc.org/cdm/ref/collection/p16829coll31/id/164</edm:isShownAt>
   <edm:preview>http://server16829.contentdm.oclc.org/cgi-bin/thumbnail.exe?CISOROOT=/p16829coll31&amp;CISOPTR=164</edm:preview>
   <dcterms:provenance>George Washington's Mount Vernon</dcterms:provenance>
</mdRecord>
